.gitignore
.hgignore
.hgtags
ABOUT.txt
CHANGES.txt
COPYRIGHT.txt
LICENSE.txt
README.txt
ROADMAP.txt
bootstrap.py
buildout.cfg
setup.py
doc/about.txt
doc/api.txt
doc/changes.txt
doc/conf.py
doc/flattr-badge-large.png
doc/index.txt
doc/interfaces.txt
doc/narrative.txt
doc/overview.txt
doc/requirements.pip
doc/roadmap.txt
doc/templates/project-links.html
example/paste.ini.in
example/wsgiref.cfg.in
example/documents/example.css
example/documents/foo/baz.html
example/templates/__init__
example/templates/index.html
example/templates/foo/__init__
example/templates/foo/bar.html
example/templates/foo/index.html
ophelia/API.txt
ophelia/CONFIGURATION.txt
ophelia/__init__.py
ophelia/input.py
ophelia/input.txt
ophelia/interfaces.py
ophelia/pagetemplate.py
ophelia/pagetemplate.txt
ophelia/request.py
ophelia/request.txt
ophelia/util.py
ophelia/util.txt
ophelia/wsgi.py
ophelia.egg-info/PKG-INFO
ophelia.egg-info/SOURCES.txt
ophelia.egg-info/dependency_links.txt
ophelia.egg-info/entry_points.txt
ophelia.egg-info/not-zip-safe
ophelia.egg-info/requires.txt
ophelia.egg-info/top_level.txt
ophelia/tests/__init__.py
ophelia/tests/test_doctests.py
ophelia/tests/test_util.py
ophelia/tests/test_wsgi.py
ophelia/tests/fixtures/documents/index.html
ophelia/tests/fixtures/documents/smoke-document.html
ophelia/tests/fixtures/documents/folder/index.html
ophelia/tests/fixtures/templates/raise.html
ophelia/tests/fixtures/templates/redirect.html
ophelia/tests/fixtures/templates/smoke.html
ophelia/tool/__init__.py
ophelia/tool/metadata.py
ophelia/tool/navigation.py
versions/versions.cfg
versions/ztk-versions-1.1.5.cfg